{
  "response": [
    {
        "maintainer": "raystef66",
        "oem": "Poco",
        "device": "Xiaomi POCO F3",
        "filename": "crDroidAndroid-11.0-20211120-alioth-v7.12.zip",
        "download": "https://sourceforge.net/projects/crdroid/files/alioth/7.x/crDroidAndroid-11.0-20211120-alioth-v7.12.zip/download",
        "timestamp": 1637410344,
        "md5": "11bc50733b46b823a81623f1aaed5245",
        "size": 1146477372,
        "version": "7.12",
        "buildtype": "Monthly",
        "forum": "https://forum.xda-developers.com/t/rom-11-0-official-alioth-crdroid-v7-5-07-05-2021.4273643/",
        "gapps": "",
        "firmware": "https://forum.xda-developers.com/t/firmware-poco-f3-xiaomi-mi-11x-redmi-k40-alioth-auto-updated.4253091/",
        "modem": "",
        "bootloader": "",
        "recovery": "https://forum.xda-developers.com/t/recovery-unofficial-twrp-3-5-1-20210702.4300189/",
        "paypal": "https://paypal.me/raystef66",
        "telegram": "https://t.me/crdroidf3"
    }
  ]
}
