{
	"response": [
		{
			"maintainer": "LinkBoi00",
			"oem": "Xiaomi",
			"device": "Mi A2 Lite",
			"filename": "crDroidAndroid-12.0-20220214-daisy-v8.2.zip",
			"download": "https://sourceforge.net/projects/crdroid/files/daisy/8.x/crDroidAndroid-12.0-20220214-daisy-v8.2.zip/download",
			"timestamp": 1644866457,
			"md5": "066bff6544432f6f0d6515673bdebe39",
			"sha256": "85abba2ddd45574b95a0f9ba6f522ca971a7649c2a3ee2fc1269f3857e23017a",
			"size": 689891405,
			"version": "8.2",
			"buildtype": "Monthly",
			"forum": "https://forum.xda-developers.com/t/official-monthly-a12-crdroid-v8-2-xiaomi-mi-a2-lite-daisy.4401933/",
			"gapps": "https://flamegapps.github.io/",
			"firmware": "https://bigota.d.miui.com/V11.0.4.0.QDLMIXM/daisy_global_images_V11.0.4.0.QDLMIXM_20200404.0000.00_10.0_88297a8e92.tgz",
			"modem": "",
			"bootloader": "",
			"recovery": "https://github.com/TWRP-Mi-A2-Lite/twrp_device_xiaomi_daisy/releases",
			"paypal": "",
			"telegram": "https://t.me/crdroid_daisy",
			"dt": "https://github.com/crdroidandroid/android_device_xiaomi_daisy",
			"common-dt": "",
			"kernel": "https://github.com/crdroidandroid/android_kernel_xiaomi_daisy"
		}
	]
}
