{
	"response": [
		{
			"maintainer": "Pranav Vashi (neobuddy89)",
			"oem": "OnePlus",
			"device": "OnePlus 5T",
			"filename": "crDroidAndroid-10.0-20200928-dumpling-v6.10.zip",
			"download": "https://sourceforge.net/projects/crdroid/files/dumpling/6.x/crDroidAndroid-10.0-20200928-dumpling-v6.10.zip/download",
			"timestamp": 1601290294,
			"md5": "470ec073545f33a21da47436affb3c42",
			"size": 872139914,
			"version": "6.10",
			"buildtype": "Monthly",
			"forum": "https://forum.xda-developers.com/oneplus-5t/development/rom-crdroid-android-6-t3972533",
			"gapps": "https://opengapps.org/",
			"firmware": "https://sourceforge.net/projects/crdroid/files/dumpling/6.x/firmware/firmware_10.0.0-H1_oneplus5T.zip/download",
			"modem": "",
			"bootloader": "",
			"recovery": "https://sourceforge.net/projects/crdroid/files/dumpling/crdroid-6.x/recovery/twrp-3.3.1-20190908-0-codeworkx-signed-forcedecrypt-dumpling.img/download",
			"paypal": "https://paypal.me/neobuddy89",
			"telegram": "https://t.me/crDroid_OnePlus5_5T"
		}
	]
}
