{
	"response": [
		{
			"maintainer": "Mrinal Ghosh (mg712702)",
			"oem": "Xiaomi",
			"device": "Redmi Note 8/8T",
			"filename": "crDroidAndroid-10.0-20200501-ginkgo-v6.5.zip",
			"download": "https://sourceforge.net/projects/crdroid/files/ginkgo/6.x/crDroidAndroid-10.0-20200501-ginkgo-v6.5.zip/download",
			"timestamp": 1588296505,
			"md5": "991baed3119bf69b787ba79f62bf8f0f",
			"size": 1042392105,
			"version": "6.5",
			"buildtype": "Monthly",
			"forum": "https://forum.xda-developers.com/redmi-note-8/development/rom-crdroidandroid-v6-5-redmi-note-8-t4082247",
			"gapps": "https://sourceforge.net/projects/opengapps/files/arm64/",
			"firmware": "",
			"modem": "",
			"bootloader": "",
			"recovery": "https://forum.xda-developers.com/redmi-note-8/development/recovery-unofficial-twrp-xiaomi-redmi-t3997267",
			"paypal": "https://paypal.me/mg712702",
			"telegram": "https://t.me/crdroidredminote8"
		}
	]
}
