{
	"response": [
		{
			"maintainer": "Lup Gabriel (gwolfu)",
			"oem": "OnePlus",
			"device": "OnePlus 7 Pro",
			"filename": "crDroidAndroid-14.0-20240414-guacamole-v10.4.zip",
			"download": "https://sourceforge.net/projects/crdroid/files/guacamole/10.x/crDroidAndroid-14.0-20240414-guacamole-v10.4.zip/download",
			"timestamp": 1713106911,
			"md5": "5d3f6d2ad1e498531ca58493b53daaec",
			"sha256": "e1619cd431c1e4d78e0dda7b7c34313971f46c82c387945a6a33376c3e7515ba",
			"size": 1213440559,
			"version": "10.4",
			"buildtype": "Weekly",
			"forum": "https://xdaforums.com/t/4640828",
			"gapps": "https://nikgapps.com/crdroid-official",
			"firmware": "https://sourceforge.net/projects/crdroid/files/guacamole/10.x/firmware/OP7Pro%20firmware%20flash%20tool%20H.41.zip/download",
			"modem": "",
			"bootloader": "",
			"recovery": "https://sourceforge.net/projects/crdroid/files/guacamole/10.x/recovery/",
			"paypal": "https://paypal.me/gwolf2u",
			"telegram": "https://t.me/crDroidOP7Pro",
			"dt": "https://github.com/crdroidandroid/android_device_oneplus_guacamole",
			"common-dt": "https://github.com/crdroidandroid/android_device_oneplus_sm8150-common",
			"kernel": "https://github.com/crdroidandroid/android_kernel_oneplus_sm8150"
		}
	]
}
