{
	"response": [
		{
			"maintainer": "Lup Gabriel (gwolfu)",
			"oem": "OnePlus",
			"device": "OnePlus 7 Pro",
			"filename": "crDroidAndroid-11.0-20201122-guacamole-v7.0.zip",
			"download": "https://sourceforge.net/projects/crdroid/files/guacamole/7.x/crDroidAndroid-11.0-20201122-guacamole-v7.0.zip/download",
			"timestamp": 1606038462,
			"md5": "2ed54c6f5fc5f890d5ba5a8ac6e75d65",
			"size": 860164516,
			"version": "7.0",
			"buildtype": "Beta",
			"forum": "https://forum.xda-developers.com/oneplus-7-pro/development/crdroid-v7-t4184671",
			"gapps": "https://sourceforge.net/projects/nikgapps/files/Releases/NikGapps-R",
			"firmware": "",
			"modem": "",
			"bootloader": "",
			"recovery": "https://forum.xda-developers.com/oneplus-7-pro/development/recovery-unofficial-twrp-recovery-t3931322",
			"paypal": "https://paypal.me/gwolf2u",
			"telegram": "https://t.me/crDroidOP7Pro"
		}
	]
}
