{
	"response": [
		{
			"maintainer": "Luke Williams (ExpressLuke)",
			"oem": "Samsung",
			"device": "Samsung Galaxy S7 Edge",
			"filename": "crDroidAndroid-11.0-20210509-hero2lte-v7.6.zip",
			"download": "https://sourceforge.net/projects/crdroid/files/hero2lte/7.x/crDroidAndroid-11.0-20210509-hero2lte-v7.6.zip/download",
			"timestamp": 1620515081,
			"md5": "9a935eacc632065e868066168362dcb3",
			"size": 723504996,
			"version": "7.6",
			"buildtype": "Monthly",
			"forum": "https://forum.xda-developers.com/t/rom-unofficial-11-crdroid-v7-2-for-samsung-galaxy-s7-edge.4187669/",
			"gapps": "",
			"firmware": "",
			"modem": "",
			"bootloader": "",
			"recovery": "",
			"paypal": "https://paypal.me/lukew594",
			"telegram": "https://t.me/expressluke8890"
		}
	]
}
