{
        "response": [
                {
                        "maintainer": "ShEV (ShevT)",
                        "oem": "OnePlus",
                        "device": "OnePlus 7T Pro",
                        "filename": "crDroidAndroid-12.1-20220430-hotdog-v8.4.zip",
                        "download": "https://sourceforge.net/projects/crdroid/files/hotdog/8.x/crDroidAndroid-12.1-20220430-hotdog-v8.4.zip/download",
                        "timestamp": 1651304076,
                        "md5": "ebe3a2a6cde51b4704b0492de41b17b6",
                        "sha256": "237d42dcec3c82d30adb7237b8067c47f3134e053030933483af2c30367eeea0",
                        "size": 1611411516,
                        "version": "8.4",
                        "buildtype": "Weekly",
                        "forum": "https://forum.xda-developers.com/t/rom-android-12-op7t-pro-official-crdroid-v8-2-20220226.4408495/",
                        "gapps": "",
                        "firmware": "",
                        "modem": "",
                        "bootloader": "",
                        "recovery": "",
                        "paypal": "",
                        "telegram": "",
                        "dt": "https://github.com/crdroidandroid/android_device_oneplus_hotdog",
                        "common-dt": "https://github.com/crdroidandroid/android_device_oneplus_sm8150-common",
                        "kernel": "https://github.com/crdroidandroid/android_kernel_oneplus_sm8150"
                }
        ]
}
