{
	"response": [
		{
			"maintainer": "Prashant",
			"oem": "Redmi",
			"device": "Redmi Note 7",
			"filename": "crDroidAndroid-13.0-20230422-lavender-v9.4.zip",
			"download": "https://sourceforge.net/projects/crdroid/files/lavender/9.x/crDroidAndroid-13.0-20230422-lavender-v9.4.zip/download",
			"timestamp": 1682119106,
			"md5": "27886a719940ee3d6af1c4058c42899f",
			"sha256": "43cd39f0569287be6888ce938a8656f38cbdfcc9d1111beebf5599267d34419c",
			"size": 1083993123,
			"version": "9.4",
			"buildtype": "Monthly",
			"forum": "https://forum.xda-developers.com/t/rom-130-official-lavender-crdroid-v9-0-26-11-2022.4523341/",
			"gapps": "",
			"firmware": "",
			"modem": "",
			"bootloader": "",
			"recovery": "https://orangefox.download/device/lavender",
			"paypal": "https://www.paypal.me/prashant1605",
			"telegram": "https://t.me/NexLav",
			"dt": "https://github.com/crdroidandroid/android_device_xiaomi_lavender",
			"common-dt": "",
			"kernel": "https://github.com/crdroidandroid/android_kernel_xiaomi_lavender"
		}
	]
}
