{
	"response": [
		{
			"maintainer": "Prashant",
			"oem": "Redmi",
			"device": "Redmi Note 7",
			"filename": "crDroidAndroid-12.1-20221013-lavender-v8.10.zip",
			"download": "https://sourceforge.net/projects/crdroid/files/lavender/8.x/crDroidAndroid-12.1-20221013-lavender-v8.10.zip/download",
			"timestamp": 1665647652,
			"md5": "b9a952cc91347c15ffbcddddf20a2850",
			"sha256": "d4afdf4e051e36bdc8c3811a3e1bd3dfb273c353e02dd832c9fce92e75135c02",
			"size": 1115758808,
			"version": "8.10",
			"buildtype": "Monthly",
			"forum": "https://forum.xda-developers.com/t/rom-12-1-official-lavender-crdroid-v8-6-25-06-2022.4464597/",
			"gapps": "",
			"firmware": "",
			"modem": "",
			"bootloader": "",
			"recovery": "https://orangefox.download/device/lavender",
			"paypal": "https://www.paypal.me/prashant1605",
			"telegram": "https://t.me/+yXeknMeipy05YTVl",
			"dt": "https://github.com/crdroidandroid/android_device_xiaomi_lavender",
			"common-dt": "",
			"kernel": "https://github.com/crdroidandroid/android_kernel_xiaomi_lavender"
		}
	]
}
