{
  "response": [
    {
        "maintainer": "K O B U X",
        "oem": "Redmi",
        "device": "Redmi 9s series (miatoll)",
        "filename": "crDroidAndroid-10.0-20201002-miatoll-v6.10.zip",
        "download": "https://sourceforge.net/projects/crdroid/files/miatoll/6.x/crDroidAndroid-10.0-20201002-miatoll-v6.10.zip/download",
        "timestamp": 1601619286,
        "md5": "03cf59e70c46cab9cda74fc400129044",
        "size": 1112951967,
        "version": "6.10",
        "buildtype": "Monthly",
        "forum": "https://forum.xda-developers.com/poco-m2-pro/development/rom-crdroid-v6-9-t4161415",
        "gapps": "https://opengapps.org/",
        "firmware": "",
        "modem": "",
        "bootloader": "",
        "recovery": "",
        "paypal": "",
        "telegram": "https://t.me/crDroidMido"
    }
  ]
}
