{
	"response": [
		{
			"maintainer": "deadlylxrd",
			"oem": "Redmi",
			"device": "Redmi 8",
			"filename": "crDroidAndroid-11.0-20210913-olive-v7.10.zip",
			"download": "https://sourceforge.net/projects/crdroid/files/olive/7.x/crDroidAndroid-11.0-20210913-olive-v7.10.zip/download",
			"timestamp": 1631533364,
			"md5": "858e95a621268532fb4c150ecacf2714",
			"size": 989014247,
			"version": "7.10",
			"buildtype": "Monthly",
			"forum": "https://forum.xda-developers.com/t/rom-los-11-0-official-olive-crdroid-v7-10-for-redmi-8.4299817/",
			"gapps": "",
			"firmware": "https://xiaomifirmwareupdater.com/firmware/olive/",
			"modem": "",
			"bootloader": "",
			"recovery": "https://eu.dl.twrp.me/olive/",
			"paypal": "https://www.paypal.me/fxcknglxrd",
			"telegram": "https://t.me/crDroid_olive"
		}
	]
}
