{
	"response": [
		{
			"maintainer": "TheForce",
			"oem": "Motorola",
			"device": "Moto G 2015",
			"filename": "crDroidAndroid-10.0-20200530-osprey-v6.6.zip",
			"download": "https://sourceforge.net/projects/crdroid/files/osprey/6.x/crDroidAndroid-10.0-20200530-osprey-v6.6.zip/download",
			"timestamp": 1590826882,
			"md5": "3496893ab9d6a84a47b4a64fb0bbd9ae",
			"size": 457395164,
			"version": "6.6",
			"buildtype": "Monthly",
			"forum": "https://forum.xda-developers.com/2015-moto-g/development/rom-t4075505",
			"gapps": "https://opengapps.org/",
			"firmware": "",
			"modem": "",
			"bootloader": "",
			"recovery": "",
			"paypal": "",
			"telegram": ""
		}
	]
}
