{
	"response": [
		{
			"maintainer": "Ayush Dubey (Ayushd70)",
			"oem": "Xiaomi",
			"device": "Redmi K20 PRO/Mi 9T PRO",
			"filename": "crDroidAndroid-10.0-20200307-raphael-v6.3.zip",
			"download": "https://sourceforge.net/projects/crdroid/files/raphael/6.x/crDroidAndroid-10.0-20200307-raphael-v6.3.zip/download",
			"timestamp": 1583566153,
			"md5": "c9c4e5154fcef9201f1edf1dd497eb25",
			"size": 629131242,
			"version": "6.3",
			"buildtype": "Stable",
			"forum": "https://forum.xda-developers.com/k20-pro/development/rom-crdroid-android-6-t4022373",
			"gapps": "https://sourceforge.net/projects/opengapps/files/arm64/beta/",
			"firmware": "https://mirror.akhilnarang.me/MIUI/raphael/",
			"modem": "",
			"bootloader": "",
			"recovery": "",
			"paypal": "https://paypal.me/ayushd70",
			"telegram": "https://t.me/raphaelpospcr"
		}
	]
}
