{
	"response": [
		{
			"maintainer": "TronFlyn",
			"oem": "Xiaomi",
			"device": "Mi 6",
			"filename": "crDroidAndroid-10.0-20200425-sagit-v6.5.zip",
			"download": "https://sourceforge.net/projects/crdroid/files/sagit/6.x/crDroidAndroid-10.0-20200425-sagit-v6.5.zip/download",
			"timestamp": 1587805963,
			"md5": "5c8fd99b6a714f2a7ab6ecf69a090e88",
			"size": 762675637,
			"version": "6.5",
			"buildtype": "Weekly",
			"forum": "https://forum.xda-developers.com/mi-6/how-to/crdroid-v6-4-t4075205",
			"gapps": "",
			"firmware": "https://tronflyn.cn/?dir=sagit/firmware",
			"modem": "",
			"bootloader": "",
			"recovery": "",
			"paypal": "https://www.paypal.me/tronflyn",
			"telegram": "https://t.me/joinchat/KTIPPhlb5WKxMxK4y2V0Cw"
		}
	]
}
