{
	"response": [
		{
			"maintainer": "竹林里有冰 (zhullyb)",
			"oem": "xiaomi",
			"device": "Xiaomi Mi 5X",
			"filename": "crDroidAndroid-10.0-20200308-tiffany-v6.4.zip",
			"download": "https://sourceforge.net/projects/crdroid/files/tiffany/6.x/crDroidAndroid-10.0-20200308-tiffany-v6.4.zip/download",
			"timestamp": 1583643942,
			"md5": "b8688d8afaa53b4c9fd12cffee0c470a",
			"size": 662586189,
			"version": "6.4",
			"buildtype": "Monthly",
			"forum": "https://forum.xda-developers.com/mi-5x/development/rom-crdroid-android-6-t4038085",
			"gapps": "https://sourceforge.net/projects/flamegapps/files/arm64/android-10/",
			"firmware": "",
			"modem": "",
			"bootloader": "",
			"recovery": "https://t.me/TiffanyUpdates/396",
			"paypal": "",
			"telegram": ""
		}
	]
}
