{
	"response": [
		{
			"maintainer": "Niteshkumar (niti)",
			"oem": "Xiaomi",
			"device": "Redmi Note 6 Pro",
			"filename": "crDroidAndroid-10.0-20200312-twolip-v6.4.zip",
			"download": "https://sourceforge.net/projects/crdroid/files/twolip/6.x/crDroidAndroid-10.0-20200312-twolip-v6.4.zip/download",
			"timestamp": 1584019264,
			"md5": "93d447800acf276ac1b241be52b7de89",
			"size": 906029464,
			"version": "6.4",
			"buildtype": "Weekly",
			"forum": "https://forum.xda-developers.com/redmi-note-6-pro/development",
			"gapps": "https://opengapps.org/",
			"firmware": "",
			"modem": "",
			"bootloader": "",
			"recovery": "",
			"paypal": "https://www.paypal.me/niti531",
			"telegram": "https://t.me/Niteshkumar15"
		}
	]
}
