{
	"response": [
		{
			"maintainer": "Fran Palmero (PacMM79)",
			"oem": "Poco",
			"device": "Poco X3 Pro",
			"filename": "crDroidAndroid-11.0-20210825-vayu-v7.9.zip",
			"download": "https://sourceforge.net/projects/crdroid/files/vayu/7.x/crDroidAndroid-11.0-20210825-vayu-v7.9.zip/download",
			"timestamp": 1629909954,
			"md5": "ea1eda529494a53152c5d76253306057",
			"size": 1160481993,
			"version": "7.9",
			"buildtype": "Weekly",
			"forum": "https://forum.xda-developers.com/t/rom-11-0-crdroid-7-6-official-vayu-bhima.4277507/",
			"gapps": "https://androidfilehost.com/?fid=2188818919693781601",
			"firmware": "https://xiaomifirmwareupdater.com/firmware/vayu/",
			"modem": "",
			"bootloader": "",
			"recovery": "https://forum.xda-developers.com/t/recovery-unofficial-alpha-teamwin-recovery-project.4269551/",
			"paypal": "https://www.paypal.com/paypalme/franpalmero",
			"telegram": "https://t.me/joinchat/5eT6QHJ9nu1kOWZk"
		}
	]
}
