{
	"response": [
		{
                        "maintainer": "Bad_Snowman",
			"oem": "Redmi",
			"device": "Note 11 Pro/Poco X4 Pro",
			"filename": "crDroidAndroid-14.0-20240821-veux-v10.7.zip",
			"download": "https://sourceforge.net/projects/crdroid/files/veux/10.x/crDroidAndroid-14.0-20240821-veux-v10.7.zip/download",
			"timestamp": 1724236125,
			"md5": "f93fe0bc829e3f07a7ef2b916cdf323a",
			"sha256": "f6976d90becca72fc1c46267bc6fc85cd3801d3a3948da3bfa4d6b322c69b21c",
			"size": 1549904954,
			"version": "10.7",
			"buildtype": "Monthly",
			"forum": "https://xdaforums.com/t/rom-14-official-crdroid-android-v10-7-veux-peux-aosp.4688026/",
			"gapps": "https://nikgapps.com/crdroid-official",
			"firmware": "https://xiaomifirmwareupdater.com/firmware/veux/",
			"modem": "",
			"bootloader": "",
			"recovery": "https://sourceforge.net/projects/crdroid/files/veux/10.x/recovery/",
			"paypal": "",
			"telegram": "https://t.me/Snowmanbuild",
			"dt": "https://github.com/crdroidandroid/android_device_xiaomi_veux",
			"common-dt": "",
			"kernel": "https://github.com/crdroidandroid/android_kernel_xiaomi_sm6375"
		}
	]
}
