{
	"response": [
		{
			"maintainer": "",
			"oem": "Redmi",
			"device": "Redmi Note 7 Pro",
			"filename": "crDroidAndroid-12.1-20221029-violet-v8.10.zip",
			"download": "https://sourceforge.net/projects/crdroid/files/violet/8.x/crDroidAndroid-12.1-20221029-violet-v8.10.zip/download",
			"timestamp": 1667056122,
			"md5": "7e09c12bf5774c320a8ba182ff582a8b",
			"sha256": "de239b088c4c1d2bef0e533a61c57afb2bc1210aa0be2b8fcfb84dd673a84d6d",
			"size": 1531039529,
			"version": "8.10",
			"buildtype": "Monthly",
			"forum": "https://forum.xda-developers.com/t/rom-12-0-crdroid-8-violet-official.4409845",
			"gapps": "https://sourceforge.net/projects/nikgapps/files/Releases/NikGapps-S/",
			"firmware": "",
			"modem": "",
			"bootloader": "",
			"recovery": "",
			"paypal": "https://paypal.me/suneeshs101",
			"telegram": "https://tx.me/crdroidviolet",
			"dt": "https://github.com/crdroidandroid/android_device_xiaomi_violet",
			"common-dt": "",
			"kernel": "https://github.com/Violet-playground/kernel_xiaomi_violet"
		}
	]
}
